nginxaccesslogparser/__init__.py
nginxaccesslogparser/__main__.py
nginxaccesslogparser/access_log.py
nginxaccesslogparser/argparser.py
nginxaccesslogparser/linear_parser.py
nginxaccesslogparser-0.9.0.dist-info/METADATA
nginxaccesslogparser-0.9.0.dist-info/RECORD
nginxaccesslogparser-0.9.0.dist-info/WHEEL
nginxaccesslogparser-0.9.0.dist-info/entry_points.txt
nginxaccesslogparser-0.9.0.dist-info/top_level.txt
